skpmem/__init__.py
skpmem/pickle_memory.py
skpmem/pmem.py
skpmem/sqlite_memory2.py
skpmem/sync_pmem.py
skpmem-0.2.0.dist-info/METADATA
skpmem-0.2.0.dist-info/WHEEL
skpmem-0.2.0.dist-info/top_level.txt
skpmem-0.2.0.dist-info/RECORD
